ionopy/__init__.py
ionopy/analysis/__init__.py
ionopy/analysis/analysis.py
ionopy/analysis/ionex.py
ionopy/process/__init__.py
ionopy/process/filename.py
ionopy/process/operations.py
ionopy-0.0.10.dist-info/LICENSE.txt
ionopy-0.0.10.dist-info/METADATA
ionopy-0.0.10.dist-info/WHEEL
ionopy-0.0.10.dist-info/top_level.txt
ionopy-0.0.10.dist-info/RECORD
